pyspring/__init__.py
pyspring/auto.py
pyspring/decorators.py
pyspring/factory_model.py
pyspring/injector.py
pyspring/registry.py
pyspring/scaner.py
pyspring/scope.py
pyspring_inject-0.0.1.dist-info/LICENSE
pyspring_inject-0.0.1.dist-info/METADATA
pyspring_inject-0.0.1.dist-info/WHEEL
pyspring_inject-0.0.1.dist-info/top_level.txt
pyspring_inject-0.0.1.dist-info/RECORD
