Metadata-Version: 2.1
Name: pyspring-inject
Version: 0.0.1
Summary: Springboot-like Dependency Injection Framework for Python
Home-page: https://github.com/weiyuhan/python-spring-inject
Author: Yuhan Wei
Author-email: Yuhan Wei <weiyuhan@pku.edu.cn>
Project-URL: Homepage, https://github.com/weiyuhan/python-spring-inject
Project-URL: Issues, https://github.com/weiyuhan/python-spring-inject/issues
Classifier: Programming Language :: Python :: 3
Classifier: License :: OSI Approved :: MIT License
Classifier: Operating System :: OS Independent
Requires-Python: >=3.8
License-File: LICENSE
Requires-Dist: pyhocon >=0.3.60
Requires-Dist: inject ==5.0.0
Provides-Extra: tests
Requires-Dist: pytest ==7.3.1 ; extra == 'tests'
Requires-Dist: black ==23.3.0 ; extra == 'tests'
Requires-Dist: mypy ==1.2.0 ; extra == 'tests'
Requires-Dist: isort ==5.12.0 ; extra == 'tests'
Requires-Dist: autoflake ==2.1.1 ; extra == 'tests'
Requires-Dist: flake8 ==6.0.0 ; extra == 'tests'
Requires-Dist: pytest-cov ==4.0.0 ; extra == 'tests'
